canirun/__init__.py
canirun/api.py
canirun/cli.py
canirun/enum.py
canirun/gpu.py
canirun/human_readable.py
canirun/logic.py
canirun-1.0.1.dist-info/licenses/LICENSE
canirun-1.0.1.dist-info/METADATA
canirun-1.0.1.dist-info/WHEEL
canirun-1.0.1.dist-info/entry_points.txt
canirun-1.0.1.dist-info/top_level.txt
canirun-1.0.1.dist-info/RECORD
