Metadata-Version: 2.4
Name: canirun
Version: 1.0.1
Summary: Check if you can run a Hugging Face model locally.
Author-email: Varun Agnihotri <hello@pythonicvarun.me>
Project-URL: Homepage, https://github.com/PythonicVarun/canirun
Project-URL: Repository, https://github.com/PythonicVarun/canirun.git
Project-URL: Issues, https://github.com/PythonicVarun/canirun/issues
Keywords: huggingface,hardware,quantization,llm,cli
Classifier: Development Status :: 3 - Alpha
Classifier: Environment :: Console
Classifier: Intended Audience :: Developers
Classifier: Intended Audience :: Science/Research
Classifier: Topic :: Scientific/Engineering :: Artificial Intelligence
Classifier: Topic :: System :: Hardware
Classifier: Programming Language :: Python :: 3
Classifier: Programming Language :: Python :: 3.10
Classifier: Programming Language :: Python :: 3.11
Classifier: Programming Language :: Python :: 3.12
Classifier: Programming Language :: Python :: 3.13
Classifier: Programming Language :: Python :: 3.14
Classifier: Operating System :: OS Independent
Classifier: License :: OSI Approved :: MIT License
Requires-Python: >=3.10
License-File: LICENSE
Requires-Dist: huggingface-hub~=1.3.1
Requires-Dist: psutil~=7.2.1
Requires-Dist: tabulate~=0.9.0
Requires-Dist: click~=8.3.1
Dynamic: license-file
